[
    {
        "id": 1,
        "name": "Cristi Aisbett",
        "cost": "PLN",
        "flavortext": null,
        "description": "Multi-lateral zero tolerance groupware",
        "usage": null,
        "price": 745.71,
        "pictures": "Sapien.jpeg",
        "inSale": true,
        "discount": 24,
        "category": null
    },
    {
        "id": 2,
        "name": "Kylie Sliney",
        "cost": "RUB",
        "flavortext": null,
        "description": "Public-key next generation paradigm",
        "usage": null,
        "price": 22.21,
        "pictures": "SedTincidunt.jpeg",
        "inSale": true,
        "discount": 6,
        "category": null
    },
    {
        "id": 3,
        "name": "Hortense Dugmore",
        "cost": "IDR",
        "flavortext": null,
        "description": "Distributed mission-critical structure",
        "usage": null,
        "price": 720.17,
        "pictures": "Morbi.png",
        "inSale": true,
        "discount": null,
        "category": null
    },
    {
        "id": 4,
        "name": "Lacey Northing",
        "cost": "RUB",
        "flavortext": "Reduced fault-tolerant data-warehouse",
        "description": "Persevering 3rd generation workforce",
        "usage": null,
        "price": 248.79,
        "pictures": "InEleifendQuam.tiff",
        "inSale": true,
        "discount": null,
        "category": null
    },
    {
        "id": 5,
        "name": "Candide Streak",
        "cost": null,
        "flavortext": "User-friendly stable encoding",
        "description": "Quality-focused motivating access",
        "usage": null,
        "price": 620.01,
        "pictures": "Vel.tiff",
        "inSale": false,
        "discount": 86,
        "category": null
    },
    {
        "id": 6,
        "name": "Leonerd Delwater",
        "cost": null,
        "flavortext": null,
        "description": "User-friendly modular protocol",
        "usage": null,
        "price": 951.13,
        "pictures": "Ultrices.tiff",
        "inSale": true,
        "discount": null,
        "category": null
    },
    {
        "id": 7,
        "name": "Kimmy Lavis",
        "cost": "NGN",
        "flavortext": null,
        "description": "Cloned composite parallelism",
        "usage": null,
        "price": 634.96,
        "pictures": "FaucibusCursus.jpeg",
        "inSale": false,
        "discount": 59,
        "category": null
    },
    {
        "id": 8,
        "name": "Tracy Dankov",
        "cost": "XOF",
        "flavortext": null,
        "description": "Mandatory radical hub",
        "usage": null,
        "price": 66.0,
        "pictures": "Luctus.jpeg",
        "inSale": true,
        "discount": null,
        "category": null
    },
    {
        "id": 9,
        "name": "Olivia Sharrier",
        "cost": "EUR",
        "flavortext": "Cross-group content-based matrices",
        "description": "Synchronised tangible collaboration",
        "usage": null,
        "price": 843.86,
        "pictures": "Ligula.png",
        "inSale": true,
        "discount": null,
        "category": null
    },
    {
        "id": 10,
        "name": "Barnebas Gillivrie",
        "cost": "EUR",
        "flavortext": null,
        "description": "Decentralized hybrid alliance",
        "usage": null,
        "price": 65.49,
        "pictures": "TinciduntNulla.tiff",
        "inSale": false,
        "discount": null,
        "category": null
    },
    {
        "id": 11,
        "name": "Rodolfo Willbond",
        "cost": "CNY",
        "flavortext": null,
        "description": "Reactive multi-tasking hierarchy",
        "usage": null,
        "price": 183.32,
        "pictures": "Ligula.jpeg",
        "inSale": true,
        "discount": null,
        "category": null
    },
    {
        "id": 12,
        "name": "Myrtice Dewicke",
        "cost": "HTG",
        "flavortext": "Synchronised dynamic infrastructure",
        "description": "Optimized tertiary complexity",
        "usage": null,
        "price": 552.52,
        "pictures": "LobortisLigulaSit.png",
        "inSale": true,
        "discount": null,
        "category": null
    },
    {
        "id": 13,
        "name": "Selby Roja",
        "cost": "CNY",
        "flavortext": null,
        "description": "Programmable homogeneous structure",
        "usage": null,
        "price": 239.17,
        "pictures": "MetusSapien.gif",
        "inSale": true,
        "discount": null,
        "category": null
    },
    {
        "id": 14,
        "name": "Neilla Losano",
        "cost": "CNY",
        "flavortext": null,
        "description": "Stand-alone asynchronous info-mediaries",
        "usage": null,
        "price": 80.99,
        "pictures": "FeugiatEt.jpeg",
        "inSale": false,
        "discount": null,
        "category": null
    },
    {
        "id": 15,
        "name": "Skipper Cavill",
        "cost": "MGA",
        "flavortext": "Enhanced optimal complexity",
        "description": "Team-oriented composite matrices",
        "usage": null,
        "price": 882.46,
        "pictures": "Faucibus.jpeg",
        "inSale": true,
        "discount": null,
        "category": null
    },
    {
        "id": 16,
        "name": "Raven Bazek",
        "cost": "CNY",
        "flavortext": "Operative cohesive benchmark",
        "description": "Balanced responsive initiative",
        "usage": null,
        "price": 654.43,
        "pictures": "Nisl.tiff",
        "inSale": false,
        "discount": null,
        "category": null
    },
    {
        "id": 17,
        "name": "Mohandas Stonier",
        "cost": "AED",
        "flavortext": "Integrated intangible orchestration",
        "description": "Profound disintermediate support",
        "usage": null,
        "price": 189.62,
        "pictures": "InFaucibusOrci.jpeg",
        "inSale": false,
        "discount": null,
        "category": null
    },
    {
        "id": 18,
        "name": "Baxter Funcheon",
        "cost": "PEN",
        "flavortext": null,
        "description": "Up-sized static initiative",
        "usage": null,
        "price": 783.67,
        "pictures": "Primis.tiff",
        "inSale": true,
        "discount": null,
        "category": null
    },
    {
        "id": 19,
        "name": "Yale Boleyn",
        "cost": "CNY",
        "flavortext": null,
        "description": "Pre-emptive context-sensitive challenge",
        "usage": null,
        "price": 848.16,
        "pictures": "Potenti.gif",
        "inSale": false,
        "discount": null,
        "category": null
    },
    {
        "id": 20,
        "name": "Raye Chattock",
        "cost": "THB",
        "flavortext": null,
        "description": "Down-sized regional encoding",
        "usage": null,
        "price": 792.99,
        "pictures": "Non.png",
        "inSale": true,
        "discount": null,
        "category": null
    },
    {
        "id": 21,
        "name": "Adoree Westell",
        "cost": "PLN",
        "flavortext": "Polarised foreground functionalities",
        "description": "User-centric contextually-based contingency",
        "usage": null,
        "price": 652.78,
        "pictures": "MaurisUllamcorper.tiff",
        "inSale": true,
        "discount": null,
        "category": null
    },
    {
        "id": 22,
        "name": "Garnette Braz",
        "cost": "CNY",
        "flavortext": null,
        "description": "Diverse dynamic open architecture",
        "usage": null,
        "price": 47.31,
        "pictures": "ElitProinRisus.png",
        "inSale": true,
        "discount": null,
        "category": null
    },
    {
        "id": 23,
        "name": "Lanita Galliford",
        "cost": null,
        "flavortext": "Future-proofed holistic encryption",
        "description": "Centralized upward-trending time-frame",
        "usage": null,
        "price": 742.92,
        "pictures": "HabitassePlateaDictumst.tiff",
        "inSale": false,
        "discount": 75,
        "category": null
    },
    {
        "id": 24,
        "name": "Curtice Guiton",
        "cost": "VND",
        "flavortext": "Digitized optimal encoding",
        "description": "Multi-lateral even-keeled product",
        "usage": null,
        "price": 890.76,
        "pictures": "JustoEtiamPretium.png",
        "inSale": false,
        "discount": 41,
        "category": null
    },
    {
        "id": 25,
        "name": "Lonny Abramchik",
        "cost": null,
        "flavortext": null,
        "description": "Advanced needs-based extranet",
        "usage": null,
        "price": 609.35,
        "pictures": "Eget.tiff",
        "inSale": false,
        "discount": null,
        "category": null
    },
    {
        "id": 26,
        "name": "Worthy Neubigging",
        "cost": "IDR",
        "flavortext": null,
        "description": "Adaptive homogeneous challenge",
        "usage": null,
        "price": 784.49,
        "pictures": "AccumsanTortor.png",
        "inSale": true,
        "discount": 2,
        "category": null
    },
    {
        "id": 27,
        "name": "Flemming Pantry",
        "cost": "PHP",
        "flavortext": "Extended reciprocal forecast",
        "description": "Intuitive user-facing database",
        "usage": null,
        "price": 298.46,
        "pictures": "In.tiff",
        "inSale": true,
        "discount": null,
        "category": null
    },
    {
        "id": 28,
        "name": "Karlotte Prosch",
        "cost": null,
        "flavortext": null,
        "description": "Pre-emptive reciprocal algorithm",
        "usage": null,
        "price": 852.07,
        "pictures": "Vulputate.tiff",
        "inSale": false,
        "discount": null,
        "category": null
    },
    {
        "id": 29,
        "name": "Buck Grumbridge",
        "cost": "XAF",
        "flavortext": null,
        "description": "User-centric 6th generation concept",
        "usage": null,
        "price": 624.4,
        "pictures": "Dui.gif",
        "inSale": true,
        "discount": null,
        "category": null
    },
    {
        "id": 30,
        "name": "Arvie Ledes",
        "cost": "IDR",
        "flavortext": null,
        "description": "Open-source upward-trending access",
        "usage": null,
        "price": 490.65,
        "pictures": "AtVelitEu.gif",
        "inSale": false,
        "discount": null,
        "category": null
    },
    {
        "id": 31,
        "name": "Rozalin Speight",
        "cost": "CNY",
        "flavortext": "Down-sized zero defect portal",
        "description": "Focused grid-enabled open architecture",
        "usage": null,
        "price": 381.64,
        "pictures": "JustoEu.gif",
        "inSale": false,
        "discount": null,
        "category": null
    },
    {
        "id": 32,
        "name": "Chevalier Ouslem",
        "cost": "BRL",
        "flavortext": "Virtual secondary application",
        "description": "Front-line bifurcated neural-net",
        "usage": null,
        "price": 23.98,
        "pictures": "UtOdio.tiff",
        "inSale": true,
        "discount": null,
        "category": null
    },
    {
        "id": 33,
        "name": "Tera Kobus",
        "cost": "SEK",
        "flavortext": null,
        "description": "Stand-alone bifurcated artificial intelligence",
        "usage": null,
        "price": 259.21,
        "pictures": "CubiliaCurae.gif",
        "inSale": true,
        "discount": null,
        "category": null
    },
    {
        "id": 34,
        "name": "Delcine Gentry",
        "cost": "ARS",
        "flavortext": null,
        "description": "Switchable secondary application",
        "usage": null,
        "price": 610.2,
        "pictures": "HendreritAtVulputate.tiff",
        "inSale": false,
        "discount": null,
        "category": null
    },
    {
        "id": 35,
        "name": "Ronnie Impy",
        "cost": "EUR",
        "flavortext": "Reduced hybrid database",
        "description": "Upgradable value-added groupware",
        "usage": null,
        "price": 897.02,
        "pictures": "SagittisSapienCum.tiff",
        "inSale": false,
        "discount": null,
        "category": null
    },
    {
        "id": 36,
        "name": "Onida Sebrook",
        "cost": "CNY",
        "flavortext": "Inverse transitional website",
        "description": "User-centric bi-directional internet solution",
        "usage": null,
        "price": 909.2,
        "pictures": "AccumsanTortorQuis.jpeg",
        "inSale": true,
        "discount": null,
        "category": null
    },
    {
        "id": 37,
        "name": "Maddalena Itter",
        "cost": "PHP",
        "flavortext": null,
        "description": "Reactive didactic complexity",
        "usage": null,
        "price": 475.5,
        "pictures": "VestibulumQuamSapien.jpeg",
        "inSale": false,
        "discount": null,
        "category": null
    },
    {
        "id": 38,
        "name": "Sheri Robbert",
        "cost": null,
        "flavortext": null,
        "description": "Persevering impactful moratorium",
        "usage": null,
        "price": 780.13,
        "pictures": "InFelisEu.png",
        "inSale": false,
        "discount": 76,
        "category": null
    },
    {
        "id": 39,
        "name": "Halette Haberjam",
        "cost": "CNY",
        "flavortext": "Organized leading edge hardware",
        "description": "Self-enabling grid-enabled budgetary management",
        "usage": null,
        "price": 775.56,
        "pictures": "PlateaDictumstEtiam.jpeg",
        "inSale": false,
        "discount": null,
        "category": null
    },
    {
        "id": 40,
        "name": "Lizette Pike",
        "cost": "ZAR",
        "flavortext": "Focused static methodology",
        "description": "Open-architected transitional archive",
        "usage": null,
        "price": 366.67,
        "pictures": "Volutpat.gif",
        "inSale": false,
        "discount": null,
        "category": null
    },
    {
        "id": 41,
        "name": "Collete Fellow",
        "cost": "JPY",
        "flavortext": null,
        "description": "Proactive multi-state project",
        "usage": null,
        "price": 933.58,
        "pictures": "SitAmet.jpeg",
        "inSale": false,
        "discount": null,
        "category": null
    },
    {
        "id": 42,
        "name": "Kerri Andersson",
        "cost": "CNY",
        "flavortext": "Visionary tertiary circuit",
        "description": "Robust empowering Graphic Interface",
        "usage": null,
        "price": 147.3,
        "pictures": "Metus.gif",
        "inSale": false,
        "discount": null,
        "category": null
    },
    {
        "id": 43,
        "name": "Max Miskimmon",
        "cost": null,
        "flavortext": null,
        "description": "Persevering mobile hierarchy",
        "usage": null,
        "price": 551.41,
        "pictures": null,
        "inSale": true,
        "discount": null,
        "category": null
    },
    {
        "id": 44,
        "name": "Cal Nono",
        "cost": "CZK",
        "flavortext": "Synergized global framework",
        "description": "Reduced neutral contingency",
        "usage": null,
        "price": 488.03,
        "pictures": "DonecQuis.gif",
        "inSale": true,
        "discount": null,
        "category": null
    },
    {
        "id": 45,
        "name": "Rikki Whelan",
        "cost": "CNY",
        "flavortext": null,
        "description": "Managed logistical methodology",
        "usage": null,
        "price": 648.51,
        "pictures": "Aliquam.tiff",
        "inSale": false,
        "discount": null,
        "category": null
    },
    {
        "id": 46,
        "name": "Cazzie MacGillespie",
        "cost": "DKK",
        "flavortext": "Assimilated context-sensitive internet solution",
        "description": "Switchable reciprocal solution",
        "usage": null,
        "price": 497.43,
        "pictures": "Ante.png",
        "inSale": true,
        "discount": 22,
        "category": null
    },
    {
        "id": 47,
        "name": "Peder Sherlaw",
        "cost": "EUR",
        "flavortext": null,
        "description": "Adaptive optimizing secured line",
        "usage": null,
        "price": 425.69,
        "pictures": "Orci.tiff",
        "inSale": false,
        "discount": 66,
        "category": null
    },
    {
        "id": 48,
        "name": "Shandee Froome",
        "cost": "IDR",
        "flavortext": null,
        "description": "Multi-channelled modular forecast",
        "usage": null,
        "price": 267.24,
        "pictures": "Accumsan.tiff",
        "inSale": false,
        "discount": null,
        "category": null
    },
    {
        "id": 49,
        "name": "Delmer Bouchier",
        "cost": null,
        "flavortext": "Diverse fault-tolerant success",
        "description": "Future-proofed fault-tolerant structure",
        "usage": null,
        "price": 656.21,
        "pictures": "VelAugueVestibulum.gif",
        "inSale": false,
        "discount": null,
        "category": null
    },
    {
        "id": 50,
        "name": "Phyllida Greest",
        "cost": "CNY",
        "flavortext": "Integrated didactic frame",
        "description": "Re-engineered radical functionalities",
        "usage": null,
        "price": 747.34,
        "pictures": "OrciMaurisLacinia.gif",
        "inSale": true,
        "discount": 16,
        "category": null
    },
    {
        "id": 51,
        "name": "Adrianna Campaigne",
        "cost": "USD",
        "flavortext": null,
        "description": "Quality-focused national solution",
        "usage": null,
        "price": 332.56,
        "pictures": "In.jpeg",
        "inSale": true,
        "discount": null,
        "category": null
    },
    {
        "id": 52,
        "name": "Marietta Pettyfer",
        "cost": "CNY",
        "flavortext": "Innovative high-level conglomeration",
        "description": "Triple-buffered mobile circuit",
        "usage": null,
        "price": 995.33,
        "pictures": "AmetNunc.gif",
        "inSale": true,
        "discount": 5,
        "category": null
    },
    {
        "id": 53,
        "name": "Meghann Ockendon",
        "cost": "CNY",
        "flavortext": null,
        "description": "Profit-focused even-keeled info-mediaries",
        "usage": null,
        "price": 441.46,
        "pictures": "ArcuSed.jpeg",
        "inSale": true,
        "discount": 11,
        "category": null
    },
    {
        "id": 54,
        "name": "Susi Meneghi",
        "cost": "PHP",
        "flavortext": "Multi-channelled mission-critical emulation",
        "description": "Assimilated executive customer loyalty",
        "usage": null,
        "price": 60.14,
        "pictures": "SemSed.gif",
        "inSale": true,
        "discount": null,
        "category": null
    },
    {
        "id": 55,
        "name": "Pennie Pallis",
        "cost": "PLN",
        "flavortext": null,
        "description": "Upgradable local structure",
        "usage": null,
        "price": 390.57,
        "pictures": "PosuereCubilia.tiff",
        "inSale": true,
        "discount": null,
        "category": null
    },
    {
        "id": 56,
        "name": "Hilary Franck",
        "cost": "EUR",
        "flavortext": "Automated content-based help-desk",
        "description": "Re-engineered regional core",
        "usage": null,
        "price": 144.44,
        "pictures": null,
        "inSale": true,
        "discount": 19,
        "category": null
    },
    {
        "id": 57,
        "name": "Maire Eddowis",
        "cost": "BRL",
        "flavortext": null,
        "description": "Virtual cohesive open architecture",
        "usage": null,
        "price": 647.18,
        "pictures": "CrasIn.jpeg",
        "inSale": true,
        "discount": 99,
        "category": null
    },
    {
        "id": 58,
        "name": "Judas Jeandon",
        "cost": "PHP",
        "flavortext": "Multi-channelled analyzing utilisation",
        "description": "Fundamental intermediate pricing structure",
        "usage": null,
        "price": 257.85,
        "pictures": "NequeLibero.png",
        "inSale": true,
        "discount": null,
        "category": null
    },
    {
        "id": 59,
        "name": "Skell Tackell",
        "cost": "RSD",
        "flavortext": null,
        "description": "Public-key multi-tasking open architecture",
        "usage": null,
        "price": 746.9,
        "pictures": "At.tiff",
        "inSale": false,
        "discount": null,
        "category": null
    },
    {
        "id": 60,
        "name": "Amelina Whate",
        "cost": "CNY",
        "flavortext": null,
        "description": "Business-focused modular knowledge base",
        "usage": null,
        "price": 631.49,
        "pictures": "ViverraDapibusNulla.jpeg",
        "inSale": true,
        "discount": null,
        "category": null
    },
    {
        "id": 61,
        "name": "See Giovannacci",
        "cost": "NZD",
        "flavortext": null,
        "description": "Progressive human-resource flexibility",
        "usage": null,
        "price": 792.63,
        "pictures": "TortorEuPede.png",
        "inSale": true,
        "discount": 20,
        "category": null
    },
    {
        "id": 62,
        "name": "Virginie Reglar",
        "cost": "IDR",
        "flavortext": null,
        "description": "Organized leading edge conglomeration",
        "usage": null,
        "price": 445.81,
        "pictures": "FelisDonecSemper.jpeg",
        "inSale": true,
        "discount": null,
        "category": null
    },
    {
        "id": 63,
        "name": "Bendicty Kordt",
        "cost": "EUR",
        "flavortext": "Enterprise-wide analyzing implementation",
        "description": "Ameliorated multi-state complexity",
        "usage": null,
        "price": 842.77,
        "pictures": null,
        "inSale": false,
        "discount": 47,
        "category": null
    },
    {
        "id": 64,
        "name": "Pandora Giacobini",
        "cost": null,
        "flavortext": null,
        "description": "Automated motivating installation",
        "usage": null,
        "price": 24.45,
        "pictures": "TinciduntEget.jpeg",
        "inSale": false,
        "discount": null,
        "category": null
    },
    {
        "id": 65,
        "name": "Hilda Howling",
        "cost": "BDT",
        "flavortext": null,
        "description": "Optimized analyzing structure",
        "usage": null,
        "price": 241.47,
        "pictures": "CuraeNullaDapibus.jpeg",
        "inSale": false,
        "discount": 25,
        "category": null
    },
    {
        "id": 66,
        "name": "Nev Karadzas",
        "cost": "BRL",
        "flavortext": null,
        "description": "Organized holistic complexity",
        "usage": null,
        "price": 96.45,
        "pictures": "VitaeQuamSuspendisse.jpeg",
        "inSale": true,
        "discount": null,
        "category": null
    },
    {
        "id": 67,
        "name": "Obie Hovington",
        "cost": "THB",
        "flavortext": "Realigned client-driven paradigm",
        "description": "Sharable next generation benchmark",
        "usage": null,
        "price": 384.68,
        "pictures": "BlanditMiIn.tiff",
        "inSale": false,
        "discount": null,
        "category": null
    },
    {
        "id": 68,
        "name": "Elfrieda Goldfinch",
        "cost": "IDR",
        "flavortext": null,
        "description": "Multi-lateral foreground archive",
        "usage": null,
        "price": 934.69,
        "pictures": "LigulaPellentesqueUltrices.jpeg",
        "inSale": false,
        "discount": null,
        "category": null
    },
    {
        "id": 69,
        "name": "Lemmie Elcoat",
        "cost": "CRC",
        "flavortext": null,
        "description": "Distributed high-level instruction set",
        "usage": null,
        "price": 639.26,
        "pictures": "Ac.gif",
        "inSale": true,
        "discount": null,
        "category": null
    },
    {
        "id": 70,
        "name": "Charissa Matuskiewicz",
        "cost": "ZAR",
        "flavortext": null,
        "description": "Extended needs-based encryption",
        "usage": null,
        "price": 671.0,
        "pictures": "Lectus.jpeg",
        "inSale": true,
        "discount": null,
        "category": null
    },
    {
        "id": 71,
        "name": "Laureen Comerford",
        "cost": "RUB",
        "flavortext": "Progressive neutral groupware",
        "description": "Face to face neutral solution",
        "usage": null,
        "price": 361.26,
        "pictures": null,
        "inSale": false,
        "discount": null,
        "category": null
    },
    {
        "id": 72,
        "name": "Fields Rebanks",
        "cost": "EUR",
        "flavortext": null,
        "description": "Business-focused didactic array",
        "usage": null,
        "price": 997.23,
        "pictures": "TurpisAdipiscingLorem.tiff",
        "inSale": true,
        "discount": null,
        "category": null
    },
    {
        "id": 73,
        "name": "Carine Rubinchik",
        "cost": null,
        "flavortext": "Polarised bifurcated ability",
        "description": "Integrated leading edge attitude",
        "usage": null,
        "price": 771.3,
        "pictures": "Vitae.tiff",
        "inSale": false,
        "discount": null,
        "category": null
    },
    {
        "id": 74,
        "name": "Storm Borne",
        "cost": null,
        "flavortext": null,
        "description": "Optimized zero defect utilisation",
        "usage": null,
        "price": 333.1,
        "pictures": "Pede.jpeg",
        "inSale": true,
        "discount": null,
        "category": null
    },
    {
        "id": 75,
        "name": "Waldo Parell",
        "cost": "EUR",
        "flavortext": "Versatile optimizing analyzer",
        "description": "Integrated demand-driven core",
        "usage": null,
        "price": 727.41,
        "pictures": "Rutrum.png",
        "inSale": true,
        "discount": 62,
        "category": null
    },
    {
        "id": 76,
        "name": "Zahara Roocroft",
        "cost": "EUR",
        "flavortext": null,
        "description": "Enhanced stable service-desk",
        "usage": null,
        "price": 986.32,
        "pictures": "Amet.gif",
        "inSale": false,
        "discount": null,
        "category": null
    },
    {
        "id": 77,
        "name": "Cobb Bettenson",
        "cost": "IDR",
        "flavortext": null,
        "description": "Customer-focused dedicated support",
        "usage": null,
        "price": 825.23,
        "pictures": "Vel.jpeg",
        "inSale": false,
        "discount": 45,
        "category": null
    },
    {
        "id": 78,
        "name": "Nick Chaffe",
        "cost": null,
        "flavortext": null,
        "description": "Realigned tangible implementation",
        "usage": null,
        "price": 324.15,
        "pictures": "AtDolor.gif",
        "inSale": true,
        "discount": null,
        "category": null
    },
    {
        "id": 79,
        "name": "Garret Padley",
        "cost": "CNY",
        "flavortext": null,
        "description": "Extended mobile task-force",
        "usage": null,
        "price": 266.16,
        "pictures": "DonecSemperSapien.gif",
        "inSale": false,
        "discount": null,
        "category": null
    },
    {
        "id": 80,
        "name": "Martie Murcutt",
        "cost": "RUB",
        "flavortext": null,
        "description": "Future-proofed 24/7 product",
        "usage": null,
        "price": 315.23,
        "pictures": "Ut.tiff",
        "inSale": false,
        "discount": null,
        "category": null
    },
    {
        "id": 81,
        "name": "Emmet Baverstock",
        "cost": "PYG",
        "flavortext": "Future-proofed even-keeled Graphical User Interface",
        "description": "Customizable encompassing parallelism",
        "usage": null,
        "price": 94.95,
        "pictures": "Porttitor.jpeg",
        "inSale": false,
        "discount": null,
        "category": null
    },
    {
        "id": 82,
        "name": "Elbertina Caseley",
        "cost": "UAH",
        "flavortext": "Upgradable zero tolerance benchmark",
        "description": "Function-based value-added paradigm",
        "usage": null,
        "price": 407.99,
        "pictures": "InMagnaBibendum.gif",
        "inSale": true,
        "discount": null,
        "category": null
    },
    {
        "id": 83,
        "name": "Kai Thomazin",
        "cost": "SEK",
        "flavortext": null,
        "description": "Automated neutral frame",
        "usage": null,
        "price": 456.44,
        "pictures": "MagnaBibendumImperdiet.png",
        "inSale": false,
        "discount": null,
        "category": null
    },
    {
        "id": 84,
        "name": "Else Hadwen",
        "cost": "BRL",
        "flavortext": null,
        "description": "Versatile disintermediate database",
        "usage": null,
        "price": 520.43,
        "pictures": "AdipiscingElit.jpeg",
        "inSale": false,
        "discount": null,
        "category": null
    },
    {
        "id": 85,
        "name": "Gill Degoix",
        "cost": "IDR",
        "flavortext": null,
        "description": "Cross-platform uniform infrastructure",
        "usage": null,
        "price": 707.55,
        "pictures": "Id.tiff",
        "inSale": false,
        "discount": null,
        "category": null
    },
    {
        "id": 86,
        "name": "Seka Poulson",
        "cost": "AFN",
        "flavortext": null,
        "description": "Fully-configurable value-added support",
        "usage": null,
        "price": 90.59,
        "pictures": "Pellentesque.gif",
        "inSale": false,
        "discount": 63,
        "category": null
    },
    {
        "id": 87,
        "name": "Arturo Fetherston",
        "cost": "IDR",
        "flavortext": null,
        "description": "Sharable optimal system engine",
        "usage": null,
        "price": 475.11,
        "pictures": "ProinAtTurpis.jpeg",
        "inSale": true,
        "discount": null,
        "category": null
    },
    {
        "id": 88,
        "name": "Tremaine Hooks",
        "cost": "CNY",
        "flavortext": null,
        "description": "Function-based holistic productivity",
        "usage": null,
        "price": 921.69,
        "pictures": "FelisDonecSemper.png",
        "inSale": true,
        "discount": null,
        "category": null
    },
    {
        "id": 89,
        "name": "Debee Newlove",
        "cost": "COP",
        "flavortext": null,
        "description": "Ergonomic optimizing firmware",
        "usage": null,
        "price": 680.43,
        "pictures": "Morbi.png",
        "inSale": true,
        "discount": 2,
        "category": null
    },
    {
        "id": 90,
        "name": "Chrissy Futter",
        "cost": "CLP",
        "flavortext": "Synergistic motivating project",
        "description": "Configurable well-modulated customer loyalty",
        "usage": null,
        "price": 172.62,
        "pictures": "Vivamus.png",
        "inSale": false,
        "discount": null,
        "category": null
    },
    {
        "id": 91,
        "name": "Lanae Filippozzi",
        "cost": "CNY",
        "flavortext": "Configurable responsive algorithm",
        "description": "Cross-group modular throughput",
        "usage": null,
        "price": 848.35,
        "pictures": "Nullam.tiff",
        "inSale": true,
        "discount": 77,
        "category": null
    },
    {
        "id": 92,
        "name": "Emmalyn Sprigings",
        "cost": "CNY",
        "flavortext": "Down-sized grid-enabled model",
        "description": "Universal secondary secured line",
        "usage": null,
        "price": 334.64,
        "pictures": "At.tiff",
        "inSale": false,
        "discount": null,
        "category": null
    },
    {
        "id": 93,
        "name": "Trevar Dishman",
        "cost": "IDR",
        "flavortext": null,
        "description": "Quality-focused actuating synergy",
        "usage": null,
        "price": 436.03,
        "pictures": "Adipiscing.jpeg",
        "inSale": false,
        "discount": 72,
        "category": null
    },
    {
        "id": 94,
        "name": "Hali Gammon",
        "cost": null,
        "flavortext": "Total bi-directional local area network",
        "description": "Intuitive client-server artificial intelligence",
        "usage": null,
        "price": 903.14,
        "pictures": "CondimentumCurabitur.gif",
        "inSale": true,
        "discount": null,
        "category": null
    },
    {
        "id": 95,
        "name": "Nedi Mobberley",
        "cost": "MKD",
        "flavortext": "Programmable holistic emulation",
        "description": "Quality-focused mission-critical strategy",
        "usage": null,
        "price": 422.28,
        "pictures": "Suscipit.jpeg",
        "inSale": true,
        "discount": 5,
        "category": null
    },
    {
        "id": 96,
        "name": "Kinnie Doggrell",
        "cost": "ARS",
        "flavortext": "Progressive disintermediate leverage",
        "description": "Front-line client-driven budgetary management",
        "usage": null,
        "price": 801.3,
        "pictures": "Lacus.jpeg",
        "inSale": false,
        "discount": null,
        "category": null
    },
    {
        "id": 97,
        "name": "Ferdinanda Beldom",
        "cost": "PLN",
        "flavortext": "Grass-roots solution-oriented open system",
        "description": "Open-source object-oriented product",
        "usage": null,
        "price": 445.71,
        "pictures": "Orci.tiff",
        "inSale": true,
        "discount": null,
        "category": null
    },
    {
        "id": 98,
        "name": "Chester Warlawe",
        "cost": "CZK",
        "flavortext": null,
        "description": "Switchable real-time framework",
        "usage": null,
        "price": 938.08,
        "pictures": "Dictumst.jpeg",
        "inSale": true,
        "discount": null,
        "category": null
    },
    {
        "id": 99,
        "name": "Giselbert Chaudron",
        "cost": "EUR",
        "flavortext": null,
        "description": "Re-contextualized methodical help-desk",
        "usage": null,
        "price": 17.72,
        "pictures": "InQuis.jpeg",
        "inSale": false,
        "discount": null,
        "category": null
    },
    {
        "id": 100,
        "name": "Sheena Cuschieri",
        "cost": "JPY",
        "flavortext": null,
        "description": "User-friendly systemic methodology",
        "usage": null,
        "price": 722.47,
        "pictures": "PurusEuMagna.jpeg",
        "inSale": false,
        "discount": null,
        "category": null
    }
]